alignment_memory/__init__.py
alignment_memory/license.py
alignment_memory/session.py
alignment_memory/a/__init__.py
alignment_memory/a/b.py
alignment_memory/a/class1.py
alignment_memory/a/class3.py
alignment_memory/auth/__init__.py
alignment_memory/auth/oidc.py
alignment_memory/cli/__init__.py
alignment_memory/cli/__main__.py
alignment_memory/cli/class1_args.py
alignment_memory/cli/cli.py
alignment_memory/cli/enterprise.py
alignment_memory/cli/search_demo.py
alignment_memory/export/__init__.py
alignment_memory/idm/__init__.py
alignment_memory/idm/connectors.py
alignment_memory/memory/__init__.py
alignment_memory/search/__init__.py
alignment_memory/sign/__init__.py
alignment_memory/sign/api.py
alignment_memory/summary/__init__.py
alignment_memory/tests/test_license.py
alignment_memory-0.1.55.dist-info/licenses/LICENSE
alignment_memory-0.1.55.dist-info/METADATA
alignment_memory-0.1.55.dist-info/WHEEL
alignment_memory-0.1.55.dist-info/entry_points.txt
alignment_memory-0.1.55.dist-info/top_level.txt
alignment_memory-0.1.55.dist-info/RECORD
