Metadata-Version: 2.4
Name: alignment_memory
Version: 0.1.55
Summary: Session-based conversation log CLI (JSONL).
Author-email: "A.B" <dev@ab.example>
License-Expression: MIT
Project-URL: Homepage, https://example.com/alignment_memory
Classifier: Programming Language :: Python :: 3
Classifier: Operating System :: OS Independent
Classifier: Environment :: Console
Classifier: Topic :: Utilities
Requires-Python: >=3.9
License-File: LICENSE
Provides-Extra: dev
Requires-Dist: pytest>=7.4; extra == "dev"
Requires-Dist: pre-commit; extra == "dev"
Requires-Dist: ruff; extra == "dev"
Requires-Dist: black; extra == "dev"
Requires-Dist: mypy; extra == "dev"
Provides-Extra: enterprise
Requires-Dist: authlib>=1.3; extra == "enterprise"
Requires-Dist: pyjwt[crypto]>=2.8; extra == "enterprise"
Requires-Dist: ldap3>=2.9; extra == "enterprise"
Requires-Dist: requests>=2.31; extra == "enterprise"
Dynamic: license-file
